zensols/grsync/resources/app.conf
zensols/grsync/__init__.py
zensols/grsync/app.py
zensols/grsync/bootstrap.py
zensols/grsync/cli.py
zensols/grsync/config.py
zensols/grsync/distmng.py
zensols/grsync/distribution.py
zensols/grsync/domain.py
zensols/grsync/freeze.py
zensols/grsync/mover.py
zensols/grsync/repospec.py
zensols/grsync/thaw.py
zensols_grsync-1.1.0.dist-info/METADATA
zensols_grsync-1.1.0.dist-info/WHEEL
zensols_grsync-1.1.0.dist-info/entry_points.txt
zensols_grsync-1.1.0.dist-info/licenses/LICENSE.md
zensols_grsync-1.1.0.dist-info/RECORD
