Metadata-Version: 2.3
Name: zensols_grsync
Version: 1.1.0
Summary: This program captures your home directory and synchronize it with another host using Git repo metadata, symbolic links and persisted files.
Project-URL: Homepage, https://github.com/plandes/grsync
Project-URL: Documentation, https://plandes.github.io/grsync
Project-URL: Repository, https://github.com/plandes/grsync.git
Project-URL: Issues, https://github.com/plandes/grsync/issues
Project-URL: Changelog, https://github.com/plandes/grsync/blob/master/CHANGELOG.md
Author-email: Paul Landes <landes@mailc.net>
License: MIT
Keywords: configuration,tooling
Requires-Python: <3.15,>=3.11
Requires-Dist: gitdb2~=2.0.3
Requires-Dist: gitpython~=3.1.29
Requires-Dist: zensols-util~=1.16.2
